[
  {"status": "Covered", "on": "08/26/2015 4:45 P.M.", "by": "Jeraid"},
  {"status": "Covered", "on": "08/26/2015 4:45 P.M.", "by": "Jeraid"},
  {"status": "Covered", "on": "08/26/2015 4:45 P.M.", "by": "Jeraid"},
  {"status": "Covered", "on": "08/26/2015 4:45 P.M.", "by": "Jeraid"},
  {"status": "Covered", "on": "08/26/2015 4:45 P.M.", "by": "Jeraid"},
  {"status": "Covered", "on": "08/26/2015 4:45 P.M.", "by": "Jeraid"},
  {"status": "Covered", "on": "08/26/2015 4:45 P.M.", "by": "Jeraid"}
]
